LICENSE
README.md
setup.py
ontopia_py/ConceptScheme.py
ontopia_py/Thing.py
ontopia_py/__init__.py
ontopia_py/ns.py
ontopia_py.egg-info/PKG-INFO
ontopia_py.egg-info/SOURCES.txt
ontopia_py.egg-info/dependency_links.txt
ontopia_py.egg-info/requires.txt
ontopia_py.egg-info/top_level.txt
ontopia_py/accesscondition/AccessCondition.py
ontopia_py/accesscondition/AdmissionType.py
ontopia_py/accesscondition/Booking.py
ontopia_py/accesscondition/OpeningHoursSpecification.py
ontopia_py/accesscondition/TemporaryClosure.py
ontopia_py/accesscondition/__init__.py
ontopia_py/acco/Accommodation.py
ontopia_py/acco/AccommodationChain.py
ontopia_py/acco/AccommodationRoom.py
ontopia_py/acco/AccommodationStarRating.py
ontopia_py/acco/AccommodationTypology.py
ontopia_py/acco/Bedroom.py
ontopia_py/acco/DoubleRoom.py
ontopia_py/acco/MeetingRoom.py
ontopia_py/acco/OSDCriterion.py
ontopia_py/acco/OSDFeature.py
ontopia_py/acco/OfferedServiceDescription.py
ontopia_py/acco/QuadrupleRoom.py
ontopia_py/acco/SingleRoom.py
ontopia_py/acco/Suite.py
ontopia_py/acco/TripleRoom.py
ontopia_py/acco/__init__.py
ontopia_py/atlasofpath/Path.py
ontopia_py/atlasofpath/PathPlan.py
ontopia_py/atlasofpath/PathStage.py
ontopia_py/atlasofpath/PathTheme.py
ontopia_py/atlasofpath/Pathway.py
ontopia_py/atlasofpath/Paving.py
ontopia_py/atlasofpath/QuantifiedPathwayPaving.py
ontopia_py/atlasofpath/Restaurant.py
ontopia_py/atlasofpath/SecurityLevel.py
ontopia_py/atlasofpath/ServiceType.py
ontopia_py/atlasofpath/Signposting.py
ontopia_py/atlasofpath/SupportService.py
ontopia_py/atlasofpath/TravellingMethod.py
ontopia_py/atlasofpath/__init__.py
ontopia_py/cis/ArchaeologicalArea.py
ontopia_py/cis/ArchaeologicalPark.py
ontopia_py/cis/Attribute.py
ontopia_py/cis/AudioObject.py
ontopia_py/cis/CISNameInTime.py
ontopia_py/cis/CISService.py
ontopia_py/cis/CISType.py
ontopia_py/cis/Catalogue.py
ontopia_py/cis/Cinema.py
ontopia_py/cis/ClericalAdministrativeArea.py
ontopia_py/cis/CollectionCulEnt.py
ontopia_py/cis/CreativeWork.py
ontopia_py/cis/CultResearchCenter.py
ontopia_py/cis/CulturalEntity.py
ontopia_py/cis/CulturalEvent.py
ontopia_py/cis/CulturalHeritageObject.py
